omero_metrics/__init__.py
omero_metrics/apps.py
omero_metrics/dash_apps/__init__.py
omero_metrics/dash_apps/dash_analyses/dash_foi/__init__.py
omero_metrics/dash_apps/dash_analyses/dash_foi/dash_dataset_foi.py
omero_metrics/dash_apps/dash_analyses/dash_foi/dash_image_foi.py
omero_metrics/dash_apps/dash_analyses/dash_psf_beads/__init__.py
omero_metrics/dash_apps/dash_analyses/dash_psf_beads/dash_dataset_psf_beads.py
omero_metrics/dash_apps/dash_analyses/dash_psf_beads/dash_image_psf_beads.py
omero_metrics/dash_apps/dash_feedback.py
omero_metrics/dash_apps/dash_forms/dash_dataset_form.py
omero_metrics/dash_apps/dash_forms/dash_group_form.py
omero_metrics/dash_apps/dash_forms/dash_project_form.py
omero_metrics/dash_apps/dash_group.py
omero_metrics/dash_apps/dash_microscope.py
omero_metrics/dash_apps/dash_multiple_projects/dash_projects.py
omero_metrics/dash_apps/dash_project.py
omero_metrics/dash_apps/dash_utils/omero_metrics_components.py
omero_metrics/forms.py
omero_metrics/middleware.py
omero_metrics/static/omero_metrics/css/sidebar.css
omero_metrics/static/omero_metrics/css/style.css
omero_metrics/static/omero_metrics/css/style_app.css
omero_metrics/static/omero_metrics/css/style_group.css
omero_metrics/static/omero_metrics/css/style_project.css
omero_metrics/static/omero_metrics/images/loader.gif
omero_metrics/static/omero_metrics/images/metrics_logo.png
omero_metrics/static/omero_metrics/images/microscope.png
omero_metrics/static/omero_metrics/images/photo.jpeg
omero_metrics/static/omero_metrics/js/js_project.js
omero_metrics/static/omero_metrics/js/sidebar.js
omero_metrics/styles.py
omero_metrics/templates/omero_metrics/dash_template_center_ui/dash_template.html
omero_metrics/templates/omero_metrics/projects.html
omero_metrics/templates/omero_metrics/top_link_template/base_nav.html
omero_metrics/templates/omero_metrics/top_link_template/imagej_template.html
omero_metrics/templates/omero_metrics/top_link_template/index.html
omero_metrics-0.2.3.dist-info/LICENSE
omero_metrics-0.2.3.dist-info/METADATA
omero_metrics-0.2.3.dist-info/WHEEL
omero_metrics-0.2.3.dist-info/RECORD
