Metadata-Version: 2.3
Name: omero-metrics
Version: 0.2.3
Summary: An OMERO webapp to follow microscope performance over time
License: GPL-3.0-only
Keywords: microscopy,metrology,OMERO
Author: Julio Mateos Langerak
Author-email: julio.mateos-langerak@igh,cnrs.fr
Maintainer: Julio Mateos Langerak
Maintainer-email: julio.mateos-langerak@igh,cnrs.fr
Requires-Python: >=3.9.18,<=3.11
Classifier: Development Status :: 2 - Pre-Alpha
Classifier: Intended Audience :: Science/Research
Classifier: License :: OSI Approved :: GNU General Public License v3 (GPLv3)
Classifier: Natural Language :: English
Classifier: Operating System :: OS Independent
Classifier: Programming Language :: Python :: 3
Classifier: Programming Language :: Python :: 3.10
Classifier: Programming Language :: Python :: 3.11
Classifier: Programming Language :: Python :: 3.12
Classifier: Programming Language :: Python :: 3.9
Classifier: Programming Language :: Python :: Implementation :: CPython
Classifier: Topic :: Scientific/Engineering :: Image Processing
Requires-Dist: bootstrap4
Requires-Dist: dash (<=2.12)
Requires-Dist: dash-bootstrap-components
Requires-Dist: dash-iconify
Requires-Dist: dash-mantine-components (==0.14.5)
Requires-Dist: dash-renderer
Requires-Dist: django-bootstrap4
Requires-Dist: django-plotly-dash (==2.4.0)
Requires-Dist: dpd_static_support (==0.0.5)
Requires-Dist: microscopemetrics (==0.2.3)
Requires-Dist: openpyxl
Requires-Dist: plotly (==5.20.0)
Project-URL: Documentation, https://montpellierressourcesimagerie.github.io/omero-metrics/
Project-URL: Homepage, https://github.com/MontpellierRessourcesImagerie/omero-metrics
Project-URL: Repository, https://github.com/MontpellierRessourcesImagerie/omero-metrics
